setup.py
src/greplin/__init__.py
src/greplin/scales/__init__.py
src/greplin/scales/aggregation.py
src/greplin/scales/aggregation_test.py
src/greplin/scales/bottlehandler.py
src/greplin/scales/flaskhandler.py
src/greplin/scales/formats.py
src/greplin/scales/formats_test.py
src/greplin/scales/graphite.py
src/greplin/scales/loop.py
src/greplin/scales/meter.py
src/greplin/scales/samplestats.py
src/greplin/scales/samplestats_test.py
src/greplin/scales/scales_test.py
src/greplin/scales/timer.py
src/greplin/scales/tornadohandler.py
src/greplin/scales/twistedweb.py
src/greplin/scales/util.py
src/greplin/scales/util_test.py
src/scales.egg-info/PKG-INFO
src/scales.egg-info/SOURCES.txt
src/scales.egg-info/dependency_links.txt
src/scales.egg-info/namespace_packages.txt
src/scales.egg-info/top_level.txt
src/scales.egg-info/zip-safe