Metadata-Version: 1.0
Name: scales
Version: 1.0.3
Summary: Stats for Python processes
Home-page: https://www.github.com/Cue/scales
Author: Greplin, Inc.
Author-email: opensource@greplin.com
License: Apache
Platform: UNKNOWN
